dirty_schema/__init__.py
dirty_schema/builder.py
dirty_schema/models.py
dirty_schema/validators.py
dirty_schema-0.2.5.dist-info/LICENSE
dirty_schema-0.2.5.dist-info/METADATA
dirty_schema-0.2.5.dist-info/WHEEL
dirty_schema-0.2.5.dist-info/top_level.txt
dirty_schema-0.2.5.dist-info/zip-safe
dirty_schema-0.2.5.dist-info/RECORD
